ispy/__init__.py
ispy/__version__.py
ispy/ispy.py
shakna_ispy-0.0.0.dist-info/METADATA
shakna_ispy-0.0.0.dist-info/WHEEL
shakna_ispy-0.0.0.dist-info/top_level.txt
shakna_ispy-0.0.0.dist-info/RECORD
