Metadata-Version: 2.1
Name: shakna-ispy
Version: 0.0.0
Summary: An S-Expression library for Python.
Home-page: https://git.sr.ht/~shakna/ispy
Author: Shakna
Author-email: s4b3r6@gmail.com
License: MIT
Platform: UNKNOWN
Classifier: License :: CC0 1.0 Universal (CC0 1.0) Public Domain Dedication
Classifier: Programming Language :: Python
Classifier: Programming Language :: Python :: 3
Classifier: Programming Language :: Python :: Implementation :: CPython
Classifier: Programming Language :: Python :: Implementation :: PyPy
Requires-Python: >=3.3.0
